[
    {
        "sub_start": 19130.0,
        "sub_end": 20284.0,
        "bestObjV": 0.004740423351091992,
        "bestParams": [
            20995.69896221161,
            0.9715902805328369,
            6.194990158081055
        ],
        "time": 2.479424
    },
    {
        "sub_start": 19187.7,
        "sub_end": 20284.0,
        "bestObjV": 0.004451224099802433,
        "bestParams": [
            21141.75382041931,
            0.9999865889549255,
            6.209901809692383
        ],
        "time": 1.394827
    },
    {
        "sub_start": 19245.4,
        "sub_end": 20284.0,
        "bestObjV": 0.0046320494836580815,
        "bestParams": [
            21092.669112205505,
            0.9999841451644897,
            6.326098442077637
        ],
        "time": 1.577475
    },
    {
        "sub_start": 19303.100000000002,
        "sub_end": 20284.0,
        "bestObjV": 0.00451180684977082,
        "bestParams": [
            21046.45962381363,
            0.9999836683273315,
            6.333869457244873
        ],
        "time": 1.026549
    },
    {
        "sub_start": 19360.800000000003,
        "sub_end": 20284.0,
        "bestObjV": 0.0045209770660567675,
        "bestParams": [
            20978.31152534485,
            0.9999726414680481,
            6.132765769958496
        ],
        "time": 2.346317
    },
    {
        "sub_start": 19418.500000000004,
        "sub_end": 20284.0,
        "bestObjV": 0.004693030731284702,
        "bestParams": [
            20964.499221086502,
            0.9999521374702454,
            6.020820140838623
        ],
        "time": 1.4509
    },
    {
        "sub_start": 19476.200000000004,
        "sub_end": 20284.0,
        "bestObjV": 0.004989639975621492,
        "bestParams": [
            20920.314554452896,
            0.9999494552612305,
            6.026607990264893
        ],
        "time": 0.855172
    },
    {
        "sub_start": 19533.900000000005,
        "sub_end": 20284.0,
        "bestObjV": 0.005102279213501679,
        "bestParams": [
            20875.988921165466,
            0.2718164920806885,
            6.005395412445068
        ],
        "time": 2.915628
    },
    {
        "sub_start": 19591.600000000006,
        "sub_end": 20284.0,
        "bestObjV": 0.005085700365551124,
        "bestParams": [
            20788.10394001007,
            0.1115923747420311,
            6.028676986694336
        ],
        "time": 0.797531
    },
    {
        "sub_start": 19649.300000000007,
        "sub_end": 20284.0,
        "bestObjV": 0.004698654847444781,
        "bestParams": [
            20563.05995130539,
            0.1784365326166153,
            6.645120143890381
        ],
        "time": 1.34302
    },
    {
        "sub_start": 19707.000000000007,
        "sub_end": 20284.0,
        "bestObjV": 0.0028849353116445794,
        "bestParams": [
            20434.424392700195,
            0.10157378017902374,
            6.0116400718688965
        ],
        "time": 2.083506
    },
    {
        "sub_start": 19764.700000000008,
        "sub_end": 20284.0,
        "bestObjV": 0.0016092911343522376,
        "bestParams": [
            20345.30673146248,
            0.10185698419809341,
            6.017859935760498
        ],
        "time": 1.114738
    },
    {
        "sub_start": 19822.40000000001,
        "sub_end": 20284.0,
        "bestObjV": 0.0014839187004724187,
        "bestParams": [
            20398.24338042736,
            0.10341309756040573,
            7.720450401306152
        ],
        "time": 0.678679
    },
    {
        "sub_start": 19880.10000000001,
        "sub_end": 20284.0,
        "bestObjV": 0.0017623865500247346,
        "bestParams": [
            20365.748063206673,
            0.10114464163780212,
            7.917267799377441
        ],
        "time": 0.641273
    },
    {
        "sub_start": 19937.80000000001,
        "sub_end": 20284.0,
        "bestObjV": 0.002559991896473722,
        "bestParams": [
            20347.50648522377,
            0.10107876360416412,
            8.380993843078613
        ],
        "time": 0.658321
    },
    {
        "sub_start": 19130.0,
        "sub_end": 20279.0,
        "bestObjV": 0.003054070901132932,
        "bestParams": [
            20311.169531226158,
            0.10263943672180176,
            8.186758041381836
        ],
        "time": 2.524946
    },
    {
        "sub_start": 19187.7,
        "sub_end": 20279.0,
        "bestObjV": 0.0029837953973092446,
        "bestParams": [
            20309.872099757195,
            0.10607772320508957,
            8.025846481323242
        ],
        "time": 1.167014
    },
    {
        "sub_start": 19245.4,
        "sub_end": 20279.0,
        "bestObjV": 0.0032727729660450367,
        "bestParams": [
            20323.478337287903,
            0.10411857068538666,
            8.569467544555664
        ],
        "time": 0.965833
    },
    {
        "sub_start": 19303.100000000002,
        "sub_end": 20279.0,
        "bestObjV": 0.006746010436252026,
        "bestParams": [
            20332.200712800026,
            0.10502377897500992,
            7.242003440856934
        ],
        "time": 1.030711
    },
    {
        "sub_start": 19360.800000000003,
        "sub_end": 20279.0,
        "bestObjV": 0.005405952939322479,
        "bestParams": [
            20312.92468905449,
            0.5825494527816772,
            6.1151814460754395
        ],
        "time": 1.062212
    },
    {
        "sub_start": 19418.500000000004,
        "sub_end": 20279.0,
        "bestObjV": 0.006260488092746052,
        "bestParams": [
            20316.800042629242,
            0.5479429364204407,
            6.07547664642334
        ],
        "time": 1.032198
    },
    {
        "sub_start": 19476.200000000004,
        "sub_end": 20279.0,
        "bestObjV": 0.006286542318647203,
        "bestParams": [
            20717.16677427292,
            0.8578364849090576,
            6.07255220413208
        ],
        "time": 1.946855
    },
    {
        "sub_start": 19533.900000000005,
        "sub_end": 20279.0,
        "bestObjV": 0.00571507854496445,
        "bestParams": [
            20786.168262004852,
            0.7466116547584534,
            6.029172420501709
        ],
        "time": 0.951823
    },
    {
        "sub_start": 19591.600000000006,
        "sub_end": 20279.0,
        "bestObjV": 0.00587282011152641,
        "bestParams": [
            20805.100586533546,
            0.8694995045661926,
            6.014076232910156
        ],
        "time": 1.364131
    },
    {
        "sub_start": 19649.300000000007,
        "sub_end": 20279.0,
        "bestObjV": 0.0060894905810093955,
        "bestParams": [
            20737.526960849762,
            0.9500922560691833,
            6.02187442779541
        ],
        "time": 0.985051
    },
    {
        "sub_start": 19707.000000000007,
        "sub_end": 20279.0,
        "bestObjV": 0.004586704865572311,
        "bestParams": [
            20514.840758800507,
            0.10768730193376541,
            6.009217262268066
        ],
        "time": 1.48658
    },
    {
        "sub_start": 19764.700000000008,
        "sub_end": 20279.0,
        "bestObjV": 0.002529944331793375,
        "bestParams": [
            20347.341971874237,
            0.10175865143537521,
            6.026214122772217
        ],
        "time": 0.917779
    },
    {
        "sub_start": 19822.40000000001,
        "sub_end": 20279.0,
        "bestObjV": 0.0020551529777921053,
        "bestParams": [
            20471.856842041016,
            0.10168103873729706,
            11.430932998657227
        ],
        "time": 0.612859
    },
    {
        "sub_start": 19880.10000000001,
        "sub_end": 20279.0,
        "bestObjV": 0.002160799944578054,
        "bestParams": [
            20398.645368099213,
            0.11153247952461243,
            6.81144380569458
        ],
        "time": 0.463077
    },
    {
        "sub_start": 19937.80000000001,
        "sub_end": 20279.0,
        "bestObjV": 0.0019676496953057575,
        "bestParams": [
            20386.420019507408,
            0.10044845193624496,
            10.414010047912598
        ],
        "time": 1.130158
    },
    {
        "sub_start": 19130.0,
        "sub_end": 20274.0,
        "bestObjV": 0.0028051496880807584,
        "bestParams": [
            20297.052220344543,
            0.1262815296649933,
            7.682084083557129
        ],
        "time": 2.379727
    },
    {
        "sub_start": 19187.7,
        "sub_end": 20274.0,
        "bestObjV": 0.0026692799657536807,
        "bestParams": [
            20300.023013591766,
            0.19989082217216492,
            7.543067932128906
        ],
        "time": 1.506449
    },
    {
        "sub_start": 19245.4,
        "sub_end": 20274.0,
        "bestObjV": 0.0022229594272448546,
        "bestParams": [
            20300.511360168457,
            0.4812176823616028,
            7.891912937164307
        ],
        "time": 1.814578
    },
    {
        "sub_start": 19303.100000000002,
        "sub_end": 20274.0,
        "bestObjV": 0.002752480043719737,
        "bestParams": [
            20300.20637178421,
            0.4471651017665863,
            7.563614368438721
        ],
        "time": 1.061774
    },
    {
        "sub_start": 19360.800000000003,
        "sub_end": 20274.0,
        "bestObjV": 0.0026054429862431366,
        "bestParams": [
            20301.568141818047,
            0.4618769586086273,
            7.187514305114746
        ],
        "time": 0.893422
    },
    {
        "sub_start": 19418.500000000004,
        "sub_end": 20274.0,
        "bestObjV": 0.005096246346774012,
        "bestParams": [
            20316.313418984413,
            0.7136411666870117,
            6.8115386962890625
        ],
        "time": 1.065036
    },
    {
        "sub_start": 19476.200000000004,
        "sub_end": 20274.0,
        "bestObjV": 0.007162473370273349,
        "bestParams": [
            20334.28410053253,
            0.5746148228645325,
            6.312014102935791
        ],
        "time": 1.126356
    },
    {
        "sub_start": 19533.900000000005,
        "sub_end": 20274.0,
        "bestObjV": 0.006315304945790094,
        "bestParams": [
            20779.05220890045,
            0.10025913268327713,
            6.366979122161865
        ],
        "time": 1.019738
    },
    {
        "sub_start": 19591.600000000006,
        "sub_end": 20274.0,
        "bestObjV": 0.005996790233017489,
        "bestParams": [
            20758.053522109985,
            0.7772819995880127,
            6.049467086791992
        ],
        "time": 4.024968
    },
    {
        "sub_start": 19649.300000000007,
        "sub_end": 20274.0,
        "bestObjV": 0.006154713105822276,
        "bestParams": [
            20761.126207351685,
            0.9951154589653015,
            6.122854232788086
        ],
        "time": 3.056054
    },
    {
        "sub_start": 19707.000000000007,
        "sub_end": 20274.0,
        "bestObjV": 0.005700971004026913,
        "bestParams": [
            20673.865670681,
            0.9760643243789673,
            6.056180000305176
        ],
        "time": 0.810446
    },
    {
        "sub_start": 19764.700000000008,
        "sub_end": 20274.0,
        "bestObjV": 0.0034490634672841754,
        "bestParams": [
            20340.835205316544,
            0.18776799738407135,
            6.049282550811768
        ],
        "time": 2.00713
    },
    {
        "sub_start": 19822.40000000001,
        "sub_end": 20274.0,
        "bestObjV": 0.002428372307124868,
        "bestParams": [
            20335.71988737583,
            0.10025027394294739,
            9.52467155456543
        ],
        "time": 0.898128
    },
    {
        "sub_start": 19880.10000000001,
        "sub_end": 20274.0,
        "bestObjV": 0.0024079763943716877,
        "bestParams": [
            20291.31239104271,
            0.10776391625404358,
            6.059223175048828
        ],
        "time": 0.924226
    },
    {
        "sub_start": 19937.80000000001,
        "sub_end": 20274.0,
        "bestObjV": 0.0018958754859828395,
        "bestParams": [
            20312.617532730103,
            0.3426804840564728,
            8.691121101379395
        ],
        "time": 0.827823
    },
    {
        "sub_start": 19130.0,
        "sub_end": 20269.0,
        "bestObjV": 0.002783695024203893,
        "bestParams": [
            20302.55461525917,
            0.17006060481071472,
            7.641321659088135
        ],
        "time": 7.233694
    },
    {
        "sub_start": 19187.7,
        "sub_end": 20269.0,
        "bestObjV": 0.002733899376536019,
        "bestParams": [
            20307.08625113964,
            0.16010409593582153,
            8.873332977294922
        ],
        "time": 1.827057
    },
    {
        "sub_start": 19245.4,
        "sub_end": 20269.0,
        "bestObjV": 0.0027339746005701797,
        "bestParams": [
            20305.43777012825,
            0.20330940186977386,
            8.696483612060547
        ],
        "time": 1.6519
    },
    {
        "sub_start": 19303.100000000002,
        "sub_end": 20269.0,
        "bestObjV": 0.003004073415509887,
        "bestParams": [
            20311.08811402321,
            0.19327792525291443,
            8.640837669372559
        ],
        "time": 1.965266
    },
    {
        "sub_start": 19360.800000000003,
        "sub_end": 20269.0,
        "bestObjV": 0.002607682918472024,
        "bestParams": [
            20305.82155895233,
            0.23673945665359497,
            7.857431411743164
        ],
        "time": 1.261188
    },
    {
        "sub_start": 19418.500000000004,
        "sub_end": 20269.0,
        "bestObjV": 0.003098122751168451,
        "bestParams": [
            20286.801386117935,
            0.17145299911499023,
            6.325557231903076
        ],
        "time": 1.194698
    },
    {
        "sub_start": 19476.200000000004,
        "sub_end": 20269.0,
        "bestObjV": 0.0027519480788470644,
        "bestParams": [
            20291.813762664795,
            0.3840320110321045,
            6.449235439300537
        ],
        "time": 1.293921
    },
    {
        "sub_start": 19533.900000000005,
        "sub_end": 20269.0,
        "bestObjV": 0.002957785435487074,
        "bestParams": [
            20295.212486624718,
            0.42270252108573914,
            6.440764904022217
        ],
        "time": 1.274788
    },
    {
        "sub_start": 19591.600000000006,
        "sub_end": 20269.0,
        "bestObjV": 0.0021740670644539257,
        "bestParams": [
            20287.99893295765,
            0.3209468722343445,
            6.301419734954834
        ],
        "time": 0.816259
    },
    {
        "sub_start": 19649.300000000007,
        "sub_end": 20269.0,
        "bestObjV": 0.002172384328127711,
        "bestParams": [
            20292.010328650475,
            0.34729358553886414,
            6.286373615264893
        ],
        "time": 0.88348
    },
    {
        "sub_start": 19707.000000000007,
        "sub_end": 20269.0,
        "bestObjV": 0.0021064804528519846,
        "bestParams": [
            20288.985748052597,
            0.30887120962142944,
            6.2199273109436035
        ],
        "time": 0.778539
    },
    {
        "sub_start": 19764.700000000008,
        "sub_end": 20269.0,
        "bestObjV": 0.0033740404476776116,
        "bestParams": [
            20329.218167304993,
            0.30637773871421814,
            6.790848731994629
        ],
        "time": 0.952082
    },
    {
        "sub_start": 19822.40000000001,
        "sub_end": 20269.0,
        "bestObjV": 0.0022120719457797426,
        "bestParams": [
            20310.6939368248,
            0.2854255139827728,
            6.1416850090026855
        ],
        "time": 0.864637
    },
    {
        "sub_start": 19880.10000000001,
        "sub_end": 20269.0,
        "bestObjV": 0.002283319132457886,
        "bestParams": [
            20365.110550880432,
            0.11694828420877457,
            6.439699172973633
        ],
        "time": 0.819859
    },
    {
        "sub_start": 19937.80000000001,
        "sub_end": 20269.0,
        "bestObjV": 0.0021493376644610156,
        "bestParams": [
            20301.320943713188,
            0.14964477717876434,
            7.912415504455566
        ],
        "time": 0.943133
    },
    {
        "sub_start": 19130.0,
        "sub_end": 20264.0,
        "bestObjV": 0.0029601490877949623,
        "bestParams": [
            20279.008729696274,
            0.30732277035713196,
            6.587821960449219
        ],
        "time": 2.441927
    },
    {
        "sub_start": 19187.7,
        "sub_end": 20264.0,
        "bestObjV": 0.002763637943677505,
        "bestParams": [
            20292.540024280548,
            0.23792096972465515,
            7.344029426574707
        ],
        "time": 1.64542
    },
    {
        "sub_start": 19245.4,
        "sub_end": 20264.0,
        "bestObjV": 0.007090294314023936,
        "bestParams": [
            20376.260466098785,
            0.182167649269104,
            8.710484504699707
        ],
        "time": 1.891629
    },
    {
        "sub_start": 19303.100000000002,
        "sub_end": 20264.0,
        "bestObjV": 0.0031115738738444333,
        "bestParams": [
            20293.77294921875,
            0.28313830494880676,
            7.324935436248779
        ],
        "time": 1.081779
    },
    {
        "sub_start": 19360.800000000003,
        "sub_end": 20264.0,
        "bestObjV": 0.0038236595952686825,
        "bestParams": [
            20340.77871656418,
            0.3018242120742798,
            11.75066089630127
        ],
        "time": 1.4606
    },
    {
        "sub_start": 19418.500000000004,
        "sub_end": 20264.0,
        "bestObjV": 0.00262216491038923,
        "bestParams": [
            20286.95920610428,
            0.6943224668502808,
            6.443198204040527
        ],
        "time": 1.34731
    },
    {
        "sub_start": 19476.200000000004,
        "sub_end": 20264.0,
        "bestObjV": 0.002627082620181148,
        "bestParams": [
            20291.730826616287,
            0.5859322547912598,
            6.833082675933838
        ],
        "time": 0.989539
    },
    {
        "sub_start": 19533.900000000005,
        "sub_end": 20264.0,
        "bestObjV": 0.0026233460679378363,
        "bestParams": [
            20289.455642938614,
            0.5990715622901917,
            6.816616535186768
        ],
        "time": 0.85263
    },
    {
        "sub_start": 19591.600000000006,
        "sub_end": 20264.0,
        "bestObjV": 0.0023766014611470983,
        "bestParams": [
            20281.269580841064,
            0.8308577537536621,
            6.273431301116943
        ],
        "time": 0.934579
    },
    {
        "sub_start": 19649.300000000007,
        "sub_end": 20264.0,
        "bestObjV": 0.0020282798926005113,
        "bestParams": [
            20284.29076075554,
            0.9399410486221313,
            6.096565246582031
        ],
        "time": 0.908498
    },
    {
        "sub_start": 19707.000000000007,
        "sub_end": 20264.0,
        "bestObjV": 0.001855203059740249,
        "bestParams": [
            20284.812962532043,
            0.8718261122703552,
            6.09798526763916
        ],
        "time": 0.994372
    },
    {
        "sub_start": 19764.700000000008,
        "sub_end": 20264.0,
        "bestObjV": 0.0017687529235733393,
        "bestParams": [
            20286.018117547035,
            0.9102169275283813,
            6.047915458679199
        ],
        "time": 0.847834
    },
    {
        "sub_start": 19822.40000000001,
        "sub_end": 20264.0,
        "bestObjV": 0.002256961620816587,
        "bestParams": [
            20304.170095801353,
            0.43158912658691406,
            6.767927169799805
        ],
        "time": 0.980201
    },
    {
        "sub_start": 19880.10000000001,
        "sub_end": 20264.0,
        "bestObjV": 0.0019985707051392246,
        "bestParams": [
            20280.622401475906,
            0.8405795693397522,
            6.059867858886719
        ],
        "time": 0.651895
    },
    {
        "sub_start": 19937.80000000001,
        "sub_end": 20264.0,
        "bestObjV": 0.0019339404466265726,
        "bestParams": [
            20480.177285671234,
            0.1815030574798584,
            9.56064510345459
        ],
        "time": 0.847044
    },
    {
        "sub_start": 19130.0,
        "sub_end": 20259.0,
        "bestObjV": 0.002789781366797055,
        "bestParams": [
            20281.679303884506,
            0.39987218379974365,
            6.287830352783203
        ],
        "time": 1.419968
    },
    {
        "sub_start": 19187.7,
        "sub_end": 20259.0,
        "bestObjV": 0.0026823518116152415,
        "bestParams": [
            20302.614424467087,
            0.1858028769493103,
            8.540525436401367
        ],
        "time": 1.975702
    },
    {
        "sub_start": 19245.4,
        "sub_end": 20259.0,
        "bestObjV": 0.0028516871626580132,
        "bestParams": [
            20300.178822517395,
            0.2670130133628845,
            8.042752265930176
        ],
        "time": 1.487861
    },
    {
        "sub_start": 19303.100000000002,
        "sub_end": 20259.0,
        "bestObjV": 0.00259192850525892,
        "bestParams": [
            20298.401482343674,
            0.3902008533477783,
            7.761693954467773
        ],
        "time": 1.05956
    },
    {
        "sub_start": 19360.800000000003,
        "sub_end": 20259.0,
        "bestObjV": 0.0026127736855713997,
        "bestParams": [
            20281.374829530716,
            0.8806114792823792,
            6.182228088378906
        ],
        "time": 1.219183
    },
    {
        "sub_start": 19418.500000000004,
        "sub_end": 20259.0,
        "bestObjV": 0.002666774304365704,
        "bestParams": [
            20282.46872806549,
            0.9512746930122375,
            6.082666873931885
        ],
        "time": 1.144491
    },
    {
        "sub_start": 19476.200000000004,
        "sub_end": 20259.0,
        "bestObjV": 0.0027292883520031595,
        "bestParams": [
            20282.19914340973,
            0.9262367486953735,
            6.050659656524658
        ],
        "time": 1.159871
    },
    {
        "sub_start": 19533.900000000005,
        "sub_end": 20259.0,
        "bestObjV": 0.002649392434198635,
        "bestParams": [
            20280.568915247917,
            0.9534203410148621,
            6.050156593322754
        ],
        "time": 1.514106
    },
    {
        "sub_start": 19591.600000000006,
        "sub_end": 20259.0,
        "bestObjV": 0.0025418299951544686,
        "bestParams": [
            20283.025526046753,
            0.9449622631072998,
            6.02284049987793
        ],
        "time": 1.060464
    },
    {
        "sub_start": 19649.300000000007,
        "sub_end": 20259.0,
        "bestObjV": 0.002374746493826174,
        "bestParams": [
            20289.40706527233,
            0.9281362891197205,
            6.0817131996154785
        ],
        "time": 0.783301
    },
    {
        "sub_start": 19707.000000000007,
        "sub_end": 20259.0,
        "bestObjV": 0.001939170595172606,
        "bestParams": [
            20283.503272294998,
            0.9723877310752869,
            6.0352654457092285
        ],
        "time": 0.715817
    },
    {
        "sub_start": 19764.700000000008,
        "sub_end": 20259.0,
        "bestObjV": 0.0016312693092884177,
        "bestParams": [
            20283.4235496521,
            0.9712742567062378,
            6.041242599487305
        ],
        "time": 0.707123
    },
    {
        "sub_start": 19822.40000000001,
        "sub_end": 20259.0,
        "bestObjV": 0.0017779737904757313,
        "bestParams": [
            20283.552276611328,
            0.9633445143699646,
            6.037206172943115
        ],
        "time": 0.706833
    },
    {
        "sub_start": 19880.10000000001,
        "sub_end": 20259.0,
        "bestObjV": 0.001849329640807089,
        "bestParams": [
            20281.0390291214,
            0.9505851864814758,
            6.037553787231445
        ],
        "time": 0.620634
    },
    {
        "sub_start": 19937.80000000001,
        "sub_end": 20259.0,
        "bestObjV": 0.0018776507002629197,
        "bestParams": [
            20327.385799884796,
            0.11588139832019806,
            9.268411636352539
        ],
        "time": 1.42504
    }
]